dbt_semantic_interfaces/__init__.py
dbt_semantic_interfaces/call_parameter_sets.py
dbt_semantic_interfaces/dataclass_serialization.py
dbt_semantic_interfaces/enum_extension.py
dbt_semantic_interfaces/errors.py
dbt_semantic_interfaces/pretty_print.py
dbt_semantic_interfaces/py.typed
dbt_semantic_interfaces/references.py
dbt_semantic_interfaces/test_utils.py
dbt_semantic_interfaces/implementations/__init__.py
dbt_semantic_interfaces/implementations/base.py
dbt_semantic_interfaces/implementations/element_config.py
dbt_semantic_interfaces/implementations/export.py
dbt_semantic_interfaces/implementations/metadata.py
dbt_semantic_interfaces/implementations/metric.py
dbt_semantic_interfaces/implementations/node_relation.py
dbt_semantic_interfaces/implementations/project_configuration.py
dbt_semantic_interfaces/implementations/saved_query.py
dbt_semantic_interfaces/implementations/semantic_manifest.py
dbt_semantic_interfaces/implementations/semantic_model.py
dbt_semantic_interfaces/implementations/semantic_version.py
dbt_semantic_interfaces/implementations/time_spine.py
dbt_semantic_interfaces/implementations/time_spine_table_configuration.py
dbt_semantic_interfaces/implementations/elements/__init__.py
dbt_semantic_interfaces/implementations/elements/dimension.py
dbt_semantic_interfaces/implementations/elements/entity.py
dbt_semantic_interfaces/implementations/elements/measure.py
dbt_semantic_interfaces/implementations/filters/__init__.py
dbt_semantic_interfaces/implementations/filters/where_filter.py
dbt_semantic_interfaces/naming/__init__.py
dbt_semantic_interfaces/naming/dundered.py
dbt_semantic_interfaces/naming/keywords.py
dbt_semantic_interfaces/parsing/__init__.py
dbt_semantic_interfaces/parsing/dir_to_model.py
dbt_semantic_interfaces/parsing/generate_json_schema_file.py
dbt_semantic_interfaces/parsing/objects.py
dbt_semantic_interfaces/parsing/schema_validator.py
dbt_semantic_interfaces/parsing/schemas.py
dbt_semantic_interfaces/parsing/yaml_loader.py
dbt_semantic_interfaces-0.10.0.dist-info/METADATA
dbt_semantic_interfaces-0.10.0.dist-info/WHEEL
dbt_semantic_interfaces-0.10.0.dist-info/licenses/LICENSE
dbt_semantic_interfaces-0.10.0.dist-info/RECORD
