Metadata-Version: 2.4
Name: dbt-semantic-interfaces
Version: 0.10.0
Summary: The shared semantic layer definitions that dbt-core and MetricFlow use
Author-email: dbt Labs <info@dbtlabs.com>
License-Expression: Apache-2.0
License-File: LICENSE
Classifier: Development Status :: 4 - Beta
Classifier: License :: OSI Approved :: Apache Software License
Classifier: Programming Language :: Python
Classifier: Programming Language :: Python :: 3.8
Classifier: Programming Language :: Python :: 3.9
Classifier: Programming Language :: Python :: 3.10
Classifier: Programming Language :: Python :: 3.11
Classifier: Programming Language :: Python :: 3.12
Classifier: Programming Language :: Python :: Implementation :: CPython
Classifier: Programming Language :: Python :: Implementation :: PyPy
Requires-Python: >=3.8
Requires-Dist: click<8.3,>=7.0
Requires-Dist: importlib-metadata<9,>=6.0
Requires-Dist: jinja2<4,>=3.1.6
Requires-Dist: jsonschema<5,>=4.0
Requires-Dist: more-itertools<11.0,>=8.0
Requires-Dist: pydantic<3,>=1.10
Requires-Dist: python-dateutil<3,>=2.0
Requires-Dist: pyyaml<7,>=6.0
Requires-Dist: typing-extensions<5,>=4.4
